british_cycling_utils/__init__.py
british_cycling_utils/club_subscription.py
british_cycling_utils-0.3.1.dist-info/METADATA
british_cycling_utils-0.3.1.dist-info/WHEEL
british_cycling_utils-0.3.1.dist-info/RECORD
