Metadata-Version: 2.4
Name: british-cycling-utils
Version: 0.3.1
Summary: Unofficial library to work with data exported from British Cycling
Author-email: elliot-100 <3186037+elliot-100@users.noreply.github.com>
Requires-Python: >=3.12
Requires-Dist: attrs>=25.3.0
Requires-Dist: cattrs>=25.2.0
